{
  "kind": "collectionType",
  "collectionName": "contacts",
  "info": {
    "singularName": "contact",
    "pluralName": "contacts",
    "displayName": "contact",
    "description": ""
  },
  "options": {
    "draftAndPublish": true
  },
  "pluginOptions": {
    "i18n": {
      "localized": true
    }
  },
  "attributes": {
    "title": {
      "type": "string",
      "pluginOptions": {
        "i18n": {
          "localized": true
        }
      }
    },
    "content": {
      "type": "text",
      "pluginOptions": {
        "i18n": {
          "localized": true
        }
      }
    },
    "email": {
      "type": "string",
      "pluginOptions": {
        "i18n": {
          "localized": true
        }
      }
    },
    "name": {
      "type": "string",
      "pluginOptions": {
        "i18n": {
          "localized": true
        }
      }
    },
    "Message": {
      "type": "string",
      "pluginOptions": {
        "i18n": {
          "localized": true
        }
      }
    }
  }
}
